LICENSE
MANIFEST.in
README.md
setup.cfg
setup.py
requirements/requirements.txt
src/os_rq_scrapy.egg-info/PKG-INFO
src/os_rq_scrapy.egg-info/SOURCES.txt
src/os_rq_scrapy.egg-info/dependency_links.txt
src/os_rq_scrapy.egg-info/entry_points.txt
src/os_rq_scrapy.egg-info/not-zip-safe
src/os_rq_scrapy.egg-info/requires.txt
src/os_rq_scrapy.egg-info/top_level.txt
src/rq_scrapy/VERSION
src/rq_scrapy/__init__.py
src/rq_scrapy/cmdline.py
src/rq_scrapy/commands/__init__.py
src/rq_scrapy/commands/crawl.py
src/rq_scrapy/commands/startproject.py
src/rq_scrapy/commands/version.py
src/rq_scrapy/cores/__init__.py
src/rq_scrapy/cores/rq_demo/__init__.py
src/rq_scrapy/cores/rq_demo/downloader.py
src/rq_scrapy/cores/rq_demo/engine.py
src/rq_scrapy/cores/rq_demo/rq.py
src/rq_scrapy/cores/rq_demo/scheduler.py
src/rq_scrapy/crawlers/__init__.py
src/rq_scrapy/crawlers/rq_demo.py
src/rq_scrapy/extensions/__init__.py
src/rq_scrapy/settings/__init__.py
src/rq_scrapy/settings/default_settings.py
src/rq_scrapy/templates/project/scrapy.cfg
src/rq_scrapy/templates/project/module/__init__.py
src/rq_scrapy/templates/project/module/items.py.tmpl
src/rq_scrapy/templates/project/module/middlewares.py.tmpl
src/rq_scrapy/templates/project/module/pipelines.py.tmpl
src/rq_scrapy/templates/project/module/settings.py.tmpl
src/rq_scrapy/templates/project/module/spiders/__init__.py
src/rq_scrapy/templates/spiders/basic.tmpl
src/rq_scrapy/templates/spiders/crawl.tmpl
src/rq_scrapy/templates/spiders/csvfeed.tmpl
src/rq_scrapy/templates/spiders/xmlfeed.tmpl
src/rq_scrapy/utils/__init__.py
src/rq_scrapy/utils/asyncio_defer.py
src/rq_scrapy/utils/rqdata.py
tests/__init__.py
tests/test_version.py