Metadata-Version: 2.1
Name: os-rq-scrapy
Version: 0.0.7
Summary: Scrapy for Request Queue
Home-page: https://github.com/cfhamlet/os-rq-scrapy
Author: Ozzy
Author-email: cfhamlet@gmail.com
License: MIT License
Platform: UNKNOWN
Classifier: Development Status :: 2 - Pre-Alpha
Classifier: Intended Audience :: Developers
Classifier: License :: OSI Approved :: MIT License
Classifier: Natural Language :: English
Classifier: Programming Language :: Python :: 3
Classifier: Programming Language :: Python :: 3.6
Classifier: Programming Language :: Python :: 3.7
Classifier: Programming Language :: Python :: 3 :: Only
Classifier: Programming Language :: Python :: Implementation :: CPython
Classifier: Programming Language :: Python :: Implementation :: PyPy
Requires-Python: >=3.6
Provides-Extra: ujson
